{
  "bghbefrghbjnsdfjgnd jgnvjdfnklvjnsfjdnvdfjksn nfvjkdfmnlnskjvndsfknvjndfs nmfdjklsnfvjnfdjn": "bghbefrghbjnsdfjgnd jgnvjdfnklvjnsfjdnvdfjksn nfvjkdfmnlnskjvndsfknvjndfs nmfdjklsnfvjnfdjn",
  "Войти": "Войти",
  "Вызвать ошибку": "Вызвать ошибку",
  "Главная страница": "Главная страница",
  "Логин": "Логин",
  "О нас": "О нас",
  "Обновить странциу": "Обновить странциу",
  "Отнять": "",
  "Пароль": "Пароль",
  "Переключатель языка": "Переключатель языка",
  "Переключатель языка сокращение": "Переключатель языка сокращение",
  "Прибавить": "",
  "Произошла ошибка": "Произошла ошибка",
  "Страница не найдена": "Страница не найдена",
  "язык": "язык"
}
